elpepep/__init__.py
elpepe-1.0.1.dist-info/LICENSE.md
elpepe-1.0.1.dist-info/METADATA
elpepe-1.0.1.dist-info/WHEEL
elpepe-1.0.1.dist-info/top_level.txt
elpepe-1.0.1.dist-info/RECORD
