Metadata-Version: 2.1
Name: elpepe
Version: 1.0.1
Summary: el pepe
Home-page: https://mathyslolbot.com
Author: Mathyslol
License: MIT
Platform: UNKNOWN
Classifier: Programming Language :: Python :: 3
Classifier: License :: OSI Approved :: MIT License
Classifier: Operating System :: OS Independent
License-File: LICENSE.md
Requires-Dist: BenBotAsync
Requires-Dist: FortniteAPIAsync
Requires-Dist: aiohttp
Requires-Dist: colorama
Requires-Dist: crayons
Requires-Dist: fortnitepy
Requires-Dist: requests
Requires-Dist: sanic (==21.6.2)
Requires-Dist: uvloop
